[
  {
    "day": 1,
    "current_city": "from West Palm Beach to White Plains",
    "transportation": "F3765519, West Palm Beach to White Plains, 2022-03-05",
    "breakfast": "-",
    "attraction": "J Harvey Turnure Memorial Park; Saxon Woods Park; Battle of White Plains Park;",
    "lunch": "The California Boulevard, White Plains",
    "dinner": "Saffron Mantra, White Plains",
    "accommodation": "Private Theatre District Bedroom, White Plains"
  },
  {
    "day": 2,
    "current_city": "White Plains",
    "transportation": "-",
    "breakfast": "Maa Vaishno Shudh Bhojnalaya, White Plains",
    "attraction": "Percy Grainger House; Greenburgh Nature Center; Neuberger Museum of Art;",
    "lunch": "El Cazador, White Plains",
    "dinner": "Mosaic - SK Premium Park, White Plains",
    "accommodation": "Spacious Studio - Midtown East, White Plains"
  },
  {
    "day": 3,
    "current_city": "from White Plains to West Palm Beach",
    "transportation": "F3755565, White Plains to West Palm Beach, 2022-03-07",
    "breakfast": "Dewan Sweets, White Plains",
    "attraction": "Kensico Dam Plaza; Playland Park; White Plains Park;",
    "lunch": "Six Pack Kitchen, White Plains",
    "dinner": "Pan Asian - Sheraton New Delhi Hotel, White Plains",
    "accommodation": "-"
  }
]
