[
  {
    "day": 1,
    "current_city": "from Buffalo to Atlanta",
    "transportation": "F3514187, 06:51-08:40",
    "breakfast": "-",
    "attraction": "World of Coca-Cola;Georgia Aquarium;Centennial Olympic Park;",
    "lunch": "Baba Au Rhum, Atlanta",
    "dinner": "Saffron, Atlanta",
    "accommodation": "Spacious private room close St. Barnabas Hospital, Atlanta"
  },
  {
    "day": 2,
    "current_city": "Atlanta",
    "transportation": "-",
    "breakfast": "Baba Au Rhum, Atlanta",
    "attraction": "Atlanta Botanical Garden;Piedmont Park;Martin Luther King, Jr. National Historical Park;",
    "lunch": "Sizzler's Ranch, Atlanta",
    "dinner": "El Pistolero, Atlanta",
    "accommodation": "Spacious private room close St. Barnabas Hospital, Atlanta"
  },
  {
    "day": 3,
    "current_city": "from Atlanta to Buffalo",
    "transportation": "F3502694, 15:47-17:42",
    "breakfast": "-",
    "attraction": "-",
    "lunch": "-",
    "dinner": "-",
    "accommodation": "-"
  }
]
