[
  {
    "day": 1,
    "current_city": "from Charlotte to Pittsburgh",
    "transportation": "Flight F4050756, Charlotte to Pittsburgh",
    "breakfast": "-",
    "attraction": "Phipps Conservatory and Botanical Gardens;The Andy Warhol Museum;Point State Park;",
    "lunch": "Burger Factory",
    "dinner": "The Urban Foundry",
    "accommodation": "Sunny 1 BR Brooklyn Loft Apartment"
  },
  {
    "day": 2,
    "current_city": "Pittsburgh",
    "transportation": "-",
    "breakfast": "Costa Coffee",
    "attraction": "Carnegie Museum of Art;The Frick Pittsburgh;Carnegie Science Center;",
    "lunch": "Burger Factory",
    "dinner": "The Urban Foundry",
    "accommodation": "Sunny 1 BR Brooklyn Loft Apartment"
  },
  {
    "day": 3,
    "current_city": "Pittsburgh",
    "transportation": "-",
    "breakfast": "Costa Coffee",
    "attraction": "Randyland;National Aviary;Trundle Manor;",
    "lunch": "Burger Factory",
    "dinner": "The Urban Foundry",
    "accommodation": "Sunny 1 BR Brooklyn Loft Apartment"
  },
  {
    "day": 4,
    "current_city": "from Pittsburgh to Erie",
    "transportation": "self-driving, Pittsburgh to Erie",
    "breakfast": "-",
    "attraction": "Presque Isle State Park;Erie Maritime Museum;Erie Zoo;",
    "lunch": "Granite City Food & Brewery",
    "dinner": "Kona Brewing Company",
    "accommodation": "INCREDIBLE TOWNHOUSE 4 STORIES 5 BEDROOMS 3 BATH"
  },
  {
    "day": 5,
    "current_city": "Erie",
    "transportation": "-",
    "breakfast": "Riyaz Chicken Corner",
    "attraction": "Tom Ridge Environmental Center at Presque Isle State Park;Presque Isle Lighthouse;Firefighters Historical Museum;",
    "lunch": "Granite City Food & Brewery",
    "dinner": "Kona Brewing Company",
    "accommodation": "INCREDIBLE TOWNHOUSE 4 STORIES 5 BEDROOMS 3 BATH"
  },
  {
    "day": 6,
    "current_city": "from Erie to Philadelphia",
    "transportation": "self-driving, Erie to Philadelphia",
    "breakfast": "-",
    "attraction": "The Franklin Institute;Independence National Historical Park;Liberty Bell;",
    "lunch": "Red Ginger Sushi, Grill & Bar",
    "dinner": "Marukame Udon",
    "accommodation": "Industrial Loft Living in NYC"
  },
  {
    "day": 7,
    "current_city": "from Philadelphia to Charlotte",
    "transportation": "Flight F3562723, Philadelphia to Charlotte",
    "breakfast": "-",
    "attraction": "Philadelphia Museum of Art;Rodin Museum;Rocky Statue;",
    "lunch": "Red Ginger Sushi, Grill & Bar",
    "dinner": "-",
    "accommodation": "-"
  }
]
