[
  {
    "day": 1,
    "current_city": "from Savannah to Houston",
    "transportation": "Flight F4011368, from Savannah to Houston",
    "breakfast": "-",
    "attraction": "Space Center Houston;Downtown Aquarium;",
    "lunch": "Jalapenos, Houston",
    "dinner": "Matchbox, Houston",
    "accommodation": "Sunny and Airy near Manhattan, Houston"
  },
  {
    "day": 2,
    "current_city": "Houston",
    "transportation": "-",
    "breakfast": "Tasty Bite, Houston",
    "attraction": "Houston Museum of Natural Science;Discovery Green;",
    "lunch": "Sheetla Dhaba, Houston",
    "dinner": "The BrewMaster - The Mix Fine Dine, Houston",
    "accommodation": "Sunny and Airy near Manhattan, Houston"
  },
  {
    "day": 3,
    "current_city": "from Houston to Longview",
    "transportation": "self-driving, from Houston to Longview",
    "breakfast": "Momo Mia, Longview",
    "attraction": "Longview World of Wonders;Longview Museum of Fine Arts;",
    "lunch": "Barbeque Nation, Longview",
    "dinner": "Apni Rasoi, Longview",
    "accommodation": "COZY HARLEM ROOM BY THE WATER - CREATIVE SPACE, Longview"
  },
  {
    "day": 4,
    "current_city": "Longview",
    "transportation": "-",
    "breakfast": "Green Chick Chop, Longview",
    "attraction": "Lear Park;Longview Arboretum and Nature Center;",
    "lunch": "Sham Sweets, Longview",
    "dinner": "Not Just Paranthas, Longview",
    "accommodation": "COZY HARLEM ROOM BY THE WATER - CREATIVE SPACE, Longview"
  },
  {
    "day": 5,
    "current_city": "from Longview to Dallas",
    "transportation": "Flight F3602892, from Longview to Dallas",
    "breakfast": "-",
    "attraction": "Dallas World Aquarium;Dallas Museum of Art;",
    "lunch": "Coconuts Fish Cafe, Dallas",
    "dinner": "Salsa Mexican Grill, Dallas",
    "accommodation": "1BR, elevator, kitchen, doorman!, Dallas"
  },
  {
    "day": 6,
    "current_city": "Dallas",
    "transportation": "-",
    "breakfast": "MONKS, Dallas",
    "attraction": "Klyde Warren Park;Perot Museum of Nature and Science;",
    "lunch": "Drifters Cafe, Dallas",
    "dinner": "L'Opera, Dallas",
    "accommodation": "1BR, elevator, kitchen, doorman!, Dallas"
  },
  {
    "day": 7,
    "current_city": "from Dallas to Savannah",
    "transportation": "Flight F3675920, from Dallas to Savannah",
    "breakfast": "-",
    "attraction": "-",
    "lunch": "-",
    "dinner": "-",
    "accommodation": "-"
  }
]
