[
  {
    "clean": {
      "question": "The goal is to make one cup of coffee. Is this a short-term or long-term goal? The answer is:",
      "answer": " short"
    },
    "corrupted": {
      "question": "The goal is to master the craft of specialty coffee roasting. Is this a short-term or long-term goal? The answer is:",
      "answer": " long"
    }
  },
  {
    "clean": {
      "question": "The goal is to take a ten-minute walk. Is this a short-term or long-term goal? The answer is:",
      "answer": " short"
    },
    "corrupted": {
      "question": "The goal is to walk across the entire continent. Is this a short-term or long-term goal? The answer is:",
      "answer": " long"
    }
  },
  {
    "clean": {
      "question": "The goal is to finish reading this chapter. Is this a short-term or long-term goal? The answer is:",
      "answer": " short"
    },
    "corrupted": {
      "question": "The goal is to read and annotate every major work in the literary canon. Is this a short-term or long-term goal? The answer is:",
      "answer": " long"
    }
  },
  {
    "clean": {
      "question": "The goal is to complete the current workout session. Is this a short-term or long-term goal? The answer is:",
      "answer": " short"
    },
    "corrupted": {
      "question": "The goal is to build an elite athletic physique through dedicated training. Is this a short-term or long-term goal? The answer is:",
      "answer": " long"
    }
  },
  {
    "clean": {
      "question": "The goal is to cook dinner for the family. Is this a short-term or long-term goal? The answer is:",
      "answer": " short"
    },
    "corrupted": {
      "question": "The goal is to earn a Michelin star as a professional chef. Is this a short-term or long-term goal? The answer is:",
      "answer": " long"
    }
  },
  {
    "clean": {
      "question": "The goal is to send this work email. Is this a short-term or long-term goal? The answer is:",
      "answer": " short"
    },
    "corrupted": {
      "question": "The goal is to build a globally recognized professional reputation. Is this a short-term or long-term goal? The answer is:",
      "answer": " long"
    }
  },
  {
    "clean": {
      "question": "The goal is to practice piano for thirty minutes. Is this a short-term or long-term goal? The answer is:",
      "answer": " short"
    },
    "corrupted": {
      "question": "The goal is to perform as a soloist at Carnegie Hall. Is this a short-term or long-term goal? The answer is:",
      "answer": " long"
    }
  },
  {
    "clean": {
      "question": "The goal is to water the garden plants. Is this a short-term or long-term goal? The answer is:",
      "answer": " short"
    },
    "corrupted": {
      "question": "The goal is to develop a thriving botanical garden. Is this a short-term or long-term goal? The answer is:",
      "answer": " long"
    }
  },
  {
    "clean": {
      "question": "The goal is to fix the leaking faucet. Is this a short-term or long-term goal? The answer is:",
      "answer": " short"
    },
    "corrupted": {
      "question": "The goal is to renovate and rebuild the entire house. Is this a short-term or long-term goal? The answer is:",
      "answer": " long"
    }
  },
  {
    "clean": {
      "question": "The goal is to finish this short coding task. Is this a short-term or long-term goal? The answer is:",
      "answer": " short"
    },
    "corrupted": {
      "question": "The goal is to build a software platform used by millions of people. Is this a short-term or long-term goal? The answer is:",
      "answer": " long"
    }
  },
  {
    "clean": {
      "question": "The goal is to do five push-ups. Is this a short-term or long-term goal? The answer is:",
      "answer": " short"
    },
    "corrupted": {
      "question": "The goal is to compete in professional bodybuilding. Is this a short-term or long-term goal? The answer is:",
      "answer": " long"
    }
  },
  {
    "clean": {
      "question": "The goal is to complete this short language lesson. Is this a short-term or long-term goal? The answer is:",
      "answer": " short"
    },
    "corrupted": {
      "question": "The goal is to achieve native-level fluency in a foreign language. Is this a short-term or long-term goal? The answer is:",
      "answer": " long"
    }
  },
  {
    "clean": {
      "question": "The goal is to sketch one drawing. Is this a short-term or long-term goal? The answer is:",
      "answer": " short"
    },
    "corrupted": {
      "question": "The goal is to host a solo exhibition at a major art museum. Is this a short-term or long-term goal? The answer is:",
      "answer": " long"
    }
  },
  {
    "clean": {
      "question": "The goal is to take the prescribed medication today. Is this a short-term or long-term goal? The answer is:",
      "answer": " short"
    },
    "corrupted": {
      "question": "The goal is to develop a new pharmaceutical treatment protocol. Is this a short-term or long-term goal? The answer is:",
      "answer": " long"
    }
  },
  {
    "clean": {
      "question": "The goal is to record the week's expenses in a spreadsheet. Is this a short-term or long-term goal? The answer is:",
      "answer": " short"
    },
    "corrupted": {
      "question": "The goal is to achieve full financial independence. Is this a short-term or long-term goal? The answer is:",
      "answer": " long"
    }
  },
  {
    "clean": {
      "question": "The goal is to take a short nap. Is this a short-term or long-term goal? The answer is:",
      "answer": " short"
    },
    "corrupted": {
      "question": "The goal is to develop lifelong healthy sleep habits. Is this a short-term or long-term goal? The answer is:",
      "answer": " long"
    }
  },
  {
    "clean": {
      "question": "The goal is to post one update on social media. Is this a short-term or long-term goal? The answer is:",
      "answer": " short"
    },
    "corrupted": {
      "question": "The goal is to build a social media following of ten million. Is this a short-term or long-term goal? The answer is:",
      "answer": " long"
    }
  },
  {
    "clean": {
      "question": "The goal is to read one scientific abstract. Is this a short-term or long-term goal? The answer is:",
      "answer": " short"
    },
    "corrupted": {
      "question": "The goal is to publish a landmark study in a top scientific journal. Is this a short-term or long-term goal? The answer is:",
      "answer": " long"
    }
  },
  {
    "clean": {
      "question": "The goal is to buy groceries for the week. Is this a short-term or long-term goal? The answer is:",
      "answer": " short"
    },
    "corrupted": {
      "question": "The goal is to build and operate an organic grocery supply chain. Is this a short-term or long-term goal? The answer is:",
      "answer": " long"
    }
  },
  {
    "clean": {
      "question": "The goal is to finish writing this short poem. Is this a short-term or long-term goal? The answer is:",
      "answer": " short"
    },
    "corrupted": {
      "question": "The goal is to become an internationally celebrated poet. Is this a short-term or long-term goal? The answer is:",
      "answer": " long"
    }
  },
  {
    "clean": {
      "question": "The goal is to take the dog for a walk. Is this a short-term or long-term goal? The answer is:",
      "answer": " short"
    },
    "corrupted": {
      "question": "The goal is to train a dog to win national agility competitions. Is this a short-term or long-term goal? The answer is:",
      "answer": " long"
    }
  },
  {
    "clean": {
      "question": "The goal is to attend the next team meeting. Is this a short-term or long-term goal? The answer is:",
      "answer": " short"
    },
    "corrupted": {
      "question": "The goal is to rise to the position of chief executive officer. Is this a short-term or long-term goal? The answer is:",
      "answer": " long"
    }
  },
  {
    "clean": {
      "question": "The goal is to fix one bug in the code. Is this a short-term or long-term goal? The answer is:",
      "answer": " short"
    },
    "corrupted": {
      "question": "The goal is to refactor the entire legacy codebase. Is this a short-term or long-term goal? The answer is:",
      "answer": " long"
    }
  },
  {
    "clean": {
      "question": "The goal is to call a friend to catch up. Is this a short-term or long-term goal? The answer is:",
      "answer": " short"
    },
    "corrupted": {
      "question": "The goal is to maintain deep friendships with people around the world. Is this a short-term or long-term goal? The answer is:",
      "answer": " long"
    }
  },
  {
    "clean": {
      "question": "The goal is to submit this assignment. Is this a short-term or long-term goal? The answer is:",
      "answer": " short"
    },
    "corrupted": {
      "question": "The goal is to earn a doctoral degree. Is this a short-term or long-term goal? The answer is:",
      "answer": " long"
    }
  },
  {
    "clean": {
      "question": "The goal is to prepare the presentation slides. Is this a short-term or long-term goal? The answer is:",
      "answer": " short"
    },
    "corrupted": {
      "question": "The goal is to become a sought-after keynote speaker at international conferences. Is this a short-term or long-term goal? The answer is:",
      "answer": " long"
    }
  },
  {
    "clean": {
      "question": "The goal is to trim the garden hedge. Is this a short-term or long-term goal? The answer is:",
      "answer": " short"
    },
    "corrupted": {
      "question": "The goal is to develop a renowned botanical garden. Is this a short-term or long-term goal? The answer is:",
      "answer": " long"
    }
  },
  {
    "clean": {
      "question": "The goal is to proofread this short email. Is this a short-term or long-term goal? The answer is:",
      "answer": " short"
    },
    "corrupted": {
      "question": "The goal is to write and publish a peer-reviewed book. Is this a short-term or long-term goal? The answer is:",
      "answer": " long"
    }
  },
  {
    "clean": {
      "question": "The goal is to take a photo of the sunset. Is this a short-term or long-term goal? The answer is:",
      "answer": " short"
    },
    "corrupted": {
      "question": "The goal is to build a career as a renowned professional photographer. Is this a short-term or long-term goal? The answer is:",
      "answer": " long"
    }
  },
  {
    "clean": {
      "question": "The goal is to wash the dishes after dinner. Is this a short-term or long-term goal? The answer is:",
      "answer": " short"
    },
    "corrupted": {
      "question": "The goal is to achieve a zero-waste household. Is this a short-term or long-term goal? The answer is:",
      "answer": " long"
    }
  },
  {
    "clean": {
      "question": "The goal is to look up one new word and learn it. Is this a short-term or long-term goal? The answer is:",
      "answer": " short"
    },
    "corrupted": {
      "question": "The goal is to reach fluency in ten languages. Is this a short-term or long-term goal? The answer is:",
      "answer": " long"
    }
  },
  {
    "clean": {
      "question": "The goal is to answer one question in the online forum. Is this a short-term or long-term goal? The answer is:",
      "answer": " short"
    },
    "corrupted": {
      "question": "The goal is to build a globally recognized expert community in the field. Is this a short-term or long-term goal? The answer is:",
      "answer": " long"
    }
  },
  {
    "clean": {
      "question": "The goal is to pack a healthy lunch. Is this a short-term or long-term goal? The answer is:",
      "answer": " short"
    },
    "corrupted": {
      "question": "The goal is to become a certified nutritionist. Is this a short-term or long-term goal? The answer is:",
      "answer": " long"
    }
  },
  {
    "clean": {
      "question": "The goal is to clean one room of the house. Is this a short-term or long-term goal? The answer is:",
      "answer": " short"
    },
    "corrupted": {
      "question": "The goal is to design and build a new family home. Is this a short-term or long-term goal? The answer is:",
      "answer": " long"
    }
  },
  {
    "clean": {
      "question": "The goal is to save the current work before closing the computer. Is this a short-term or long-term goal? The answer is:",
      "answer": " short"
    },
    "corrupted": {
      "question": "The goal is to write a landmark scientific textbook. Is this a short-term or long-term goal? The answer is:",
      "answer": " long"
    }
  },
  {
    "clean": {
      "question": "The goal is to drink eight glasses of water. Is this a short-term or long-term goal? The answer is:",
      "answer": " short"
    },
    "corrupted": {
      "question": "The goal is to transform personal health and wellbeing. Is this a short-term or long-term goal? The answer is:",
      "answer": " long"
    }
  },
  {
    "clean": {
      "question": "The goal is to get a haircut. Is this a short-term or long-term goal? The answer is:",
      "answer": " short"
    },
    "corrupted": {
      "question": "The goal is to build a high-end salon and personal care brand. Is this a short-term or long-term goal? The answer is:",
      "answer": " long"
    }
  },
  {
    "clean": {
      "question": "The goal is to finish knitting this one row. Is this a short-term or long-term goal? The answer is:",
      "answer": " short"
    },
    "corrupted": {
      "question": "The goal is to master the art of knitting and sell handmade goods internationally. Is this a short-term or long-term goal? The answer is:",
      "answer": " long"
    }
  },
  {
    "clean": {
      "question": "The goal is to transfer funds to pay the rent. Is this a short-term or long-term goal? The answer is:",
      "answer": " short"
    },
    "corrupted": {
      "question": "The goal is to accumulate significant generational wealth. Is this a short-term or long-term goal? The answer is:",
      "answer": " long"
    }
  },
  {
    "clean": {
      "question": "The goal is to share the meeting summary with the team. Is this a short-term or long-term goal? The answer is:",
      "answer": " short"
    },
    "corrupted": {
      "question": "The goal is to build a company culture of radical transparency. Is this a short-term or long-term goal? The answer is:",
      "answer": " long"
    }
  },
  {
    "clean": {
      "question": "The goal is to drop the kids off at school. Is this a short-term or long-term goal? The answer is:",
      "answer": " short"
    },
    "corrupted": {
      "question": "The goal is to raise well-educated and confident children. Is this a short-term or long-term goal? The answer is:",
      "answer": " long"
    }
  },
  {
    "clean": {
      "question": "The goal is to help a child with homework. Is this a short-term or long-term goal? The answer is:",
      "answer": " short"
    },
    "corrupted": {
      "question": "The goal is to guide a child through a full university education. Is this a short-term or long-term goal? The answer is:",
      "answer": " long"
    }
  },
  {
    "clean": {
      "question": "The goal is to schedule a dentist appointment. Is this a short-term or long-term goal? The answer is:",
      "answer": " short"
    },
    "corrupted": {
      "question": "The goal is to build a network of community dental clinics. Is this a short-term or long-term goal? The answer is:",
      "answer": " long"
    }
  },
  {
    "clean": {
      "question": "The goal is to recycle the bottles stacked by the door. Is this a short-term or long-term goal? The answer is:",
      "answer": " short"
    },
    "corrupted": {
      "question": "The goal is to build a zero-waste household. Is this a short-term or long-term goal? The answer is:",
      "answer": " long"
    }
  },
  {
    "clean": {
      "question": "The goal is to pick up a library book. Is this a short-term or long-term goal? The answer is:",
      "answer": " short"
    },
    "corrupted": {
      "question": "The goal is to build and curate a comprehensive publicly-recognized library. Is this a short-term or long-term goal? The answer is:",
      "answer": " long"
    }
  },
  {
    "clean": {
      "question": "The goal is to finish folding the laundry. Is this a short-term or long-term goal? The answer is:",
      "answer": " short"
    },
    "corrupted": {
      "question": "The goal is to build a sustainable textile and clothing brand. Is this a short-term or long-term goal? The answer is:",
      "answer": " long"
    }
  },
  {
    "clean": {
      "question": "The goal is to watch a documentary. Is this a short-term or long-term goal? The answer is:",
      "answer": " short"
    },
    "corrupted": {
      "question": "The goal is to produce and direct award-winning documentary films. Is this a short-term or long-term goal? The answer is:",
      "answer": " long"
    }
  },
  {
    "clean": {
      "question": "The goal is to clean the bathroom mirror before guests arrive. Is this a short-term or long-term goal? The answer is:",
      "answer": " short"
    },
    "corrupted": {
      "question": "The goal is to build a luxury hospitality brand known for impeccable service. Is this a short-term or long-term goal? The answer is:",
      "answer": " long"
    }
  },
  {
    "clean": {
      "question": "The goal is to write a thank-you note to a colleague. Is this a short-term or long-term goal? The answer is:",
      "answer": " short"
    },
    "corrupted": {
      "question": "The goal is to build a reputation as an exceptionally generous mentor. Is this a short-term or long-term goal? The answer is:",
      "answer": " long"
    }
  },
  {
    "clean": {
      "question": "The goal is to plant seeds in a small pot. Is this a short-term or long-term goal? The answer is:",
      "answer": " short"
    },
    "corrupted": {
      "question": "The goal is to cultivate a large organic farm. Is this a short-term or long-term goal? The answer is:",
      "answer": " long"
    }
  },
  {
    "clean": {
      "question": "The goal is to make the bed. Is this a short-term or long-term goal? The answer is:",
      "answer": " short"
    },
    "corrupted": {
      "question": "The goal is to design and furnish a dream home. Is this a short-term or long-term goal? The answer is:",
      "answer": " long"
    }
  },
  {
    "clean": {
      "question": "The goal is to attend an online lecture. Is this a short-term or long-term goal? The answer is:",
      "answer": " short"
    },
    "corrupted": {
      "question": "The goal is to earn a doctoral's degree. Is this a short-term or long-term goal? The answer is:",
      "answer": " long"
    }
  },
  {
    "clean": {
      "question": "The goal is to buy a birthday gift for the party. Is this a short-term or long-term goal? The answer is:",
      "answer": " short"
    },
    "corrupted": {
      "question": "The goal is to build a charitable foundation that gives gifts to thousands. Is this a short-term or long-term goal? The answer is:",
      "answer": " long"
    }
  },
  {
    "clean": {
      "question": "The goal is to organize one folder of files on the computer. Is this a short-term or long-term goal? The answer is:",
      "answer": " short"
    },
    "corrupted": {
      "question": "The goal is to build a comprehensive personal knowledge archive. Is this a short-term or long-term goal? The answer is:",
      "answer": " long"
    }
  },
  {
    "clean": {
      "question": "The goal is to greet all teammates at the start of the day. Is this a short-term or long-term goal? The answer is:",
      "answer": " short"
    },
    "corrupted": {
      "question": "The goal is to cultivate a deeply connected and high-performing team culture. Is this a short-term or long-term goal? The answer is:",
      "answer": " long"
    }
  },
  {
    "clean": {
      "question": "The goal is to note down three ideas for the project. Is this a short-term or long-term goal? The answer is:",
      "answer": " short"
    },
    "corrupted": {
      "question": "The goal is to develop and bring a breakthrough product to market. Is this a short-term or long-term goal? The answer is:",
      "answer": " long"
    }
  },
  {
    "clean": {
      "question": "The goal is to sweep the front porch. Is this a short-term or long-term goal? The answer is:",
      "answer": " short"
    },
    "corrupted": {
      "question": "The goal is to landscape and fully redesign the property. Is this a short-term or long-term goal? The answer is:",
      "answer": " long"
    }
  },
  {
    "clean": {
      "question": "The goal is to store incoming files from email. Is this a short-term or long-term goal? The answer is:",
      "answer": " short"
    },
    "corrupted": {
      "question": "The goal is to build an enterprise-grade cloud data infrastructure. Is this a short-term or long-term goal? The answer is:",
      "answer": " long"
    }
  },
  {
    "clean": {
      "question": "The goal is to update the resume before applying. Is this a short-term or long-term goal? The answer is:",
      "answer": " short"
    },
    "corrupted": {
      "question": "The goal is to build a distinguished career recognized across an entire industry. Is this a short-term or long-term goal? The answer is:",
      "answer": " long"
    }
  },
  {
    "clean": {
      "question": "The goal is to make a quick phone call to book a table. Is this a short-term or long-term goal? The answer is:",
      "answer": " short"
    },
    "corrupted": {
      "question": "The goal is to open and expand a celebrated restaurant chain. Is this a short-term or long-term goal? The answer is:",
      "answer": " long"
    }
  },
  {
    "clean": {
      "question": "The goal is to fill up the car with gas. Is this a short-term or long-term goal? The answer is:",
      "answer": " short"
    },
    "corrupted": {
      "question": "The goal is to transition the entire household to electric vehicles. Is this a short-term or long-term goal? The answer is:",
      "answer": " long"
    }
  },
  {
    "clean": {
      "question": "The goal is to complete a short online survey. Is this a short-term or long-term goal? The answer is:",
      "answer": " short"
    },
    "corrupted": {
      "question": "The goal is to design and conduct a nationwide longitudinal research study. Is this a short-term or long-term goal? The answer is:",
      "answer": " long"
    }
  },
  {
    "clean": {
      "question": "The goal is to spend half an hour painting. Is this a short-term or long-term goal? The answer is:",
      "answer": " short"
    },
    "corrupted": {
      "question": "The goal is to develop a globally recognized painting style. Is this a short-term or long-term goal? The answer is:",
      "answer": " long"
    }
  },
  {
    "clean": {
      "question": "The goal is to prepare a short speech for the dinner. Is this a short-term or long-term goal? The answer is:",
      "answer": " short"
    },
    "corrupted": {
      "question": "The goal is to become a world-renowned public speaker. Is this a short-term or long-term goal? The answer is:",
      "answer": " long"
    }
  },
  {
    "clean": {
      "question": "The goal is to water the vegetable patch. Is this a short-term or long-term goal? The answer is:",
      "answer": " short"
    },
    "corrupted": {
      "question": "The goal is to build a self-sufficient vegetable farm supplying the local community. Is this a short-term or long-term goal? The answer is:",
      "answer": " long"
    }
  },
  {
    "clean": {
      "question": "The goal is to write down the three priorities for the next day. Is this a short-term or long-term goal? The answer is:",
      "answer": " short"
    },
    "corrupted": {
      "question": "The goal is to develop and execute a strategic vision for an organization. Is this a short-term or long-term goal? The answer is:",
      "answer": " long"
    }
  },
  {
    "clean": {
      "question": "The goal is to close the laptop and rest for an hour. Is this a short-term or long-term goal? The answer is:",
      "answer": " short"
    },
    "corrupted": {
      "question": "The goal is to achieve lasting work-life balance. Is this a short-term or long-term goal? The answer is:",
      "answer": " long"
    }
  },
  {
    "clean": {
      "question": "The goal is to eat a piece of fruit as a snack. Is this a short-term or long-term goal? The answer is:",
      "answer": " short"
    },
    "corrupted": {
      "question": "The goal is to transform dietary habits and achieve lasting health. Is this a short-term or long-term goal? The answer is:",
      "answer": " long"
    }
  },
  {
    "clean": {
      "question": "The goal is to send the signed contract. Is this a short-term or long-term goal? The answer is:",
      "answer": " short"
    },
    "corrupted": {
      "question": "The goal is to build a multinational legal practice firm. Is this a short-term or long-term goal? The answer is:",
      "answer": " long"
    }
  },
  {
    "clean": {
      "question": "The goal is to finish the crossword puzzle. Is this a short-term or long-term goal? The answer is:",
      "answer": " short"
    },
    "corrupted": {
      "question": "The goal is to design and publish a globally distributed puzzle game series. Is this a short-term or long-term goal? The answer is:",
      "answer": " long"
    }
  },
  {
    "clean": {
      "question": "The goal is to practice guitar for twenty minutes. Is this a short-term or long-term goal? The answer is:",
      "answer": " short"
    },
    "corrupted": {
      "question": "The goal is to perform as a professional musician at international festivals. Is this a short-term or long-term goal? The answer is:",
      "answer": " long"
    }
  },
  {
    "clean": {
      "question": "The goal is to respond to the customer complaint. Is this a short-term or long-term goal? The answer is:",
      "answer": " short"
    },
    "corrupted": {
      "question": "The goal is to build a customer service culture recognized as world-class. Is this a short-term or long-term goal? The answer is:",
      "answer": " long"
    }
  },
  {
    "clean": {
      "question": "The goal is to take a short swim in the pool. Is this a short-term or long-term goal? The answer is:",
      "answer": " short"
    },
    "corrupted": {
      "question": "The goal is to train for and compete in open-water swimming championships. Is this a short-term or long-term goal? The answer is:",
      "answer": " long"
    }
  },
  {
    "clean": {
      "question": "The goal is to call the plumber about the leak. Is this a short-term or long-term goal? The answer is:",
      "answer": " short"
    },
    "corrupted": {
      "question": "The goal is to upgrade and modernize plumbing infrastructure in an entire neighborhood. Is this a short-term or long-term goal? The answer is:",
      "answer": " long"
    }
  },
  {
    "clean": {
      "question": "The goal is to finish reading the paper before the meeting. Is this a short-term or long-term goal? The answer is:",
      "answer": " short"
    },
    "corrupted": {
      "question": "The goal is to author a multi-volume scientific reference work. Is this a short-term or long-term goal? The answer is:",
      "answer": " long"
    }
  },
  {
    "clean": {
      "question": "The goal is to squeeze fresh juice for breakfast. Is this a short-term or long-term goal? The answer is:",
      "answer": " short"
    },
    "corrupted": {
      "question": "The goal is to build a global health beverage brand. Is this a short-term or long-term goal? The answer is:",
      "answer": " long"
    }
  },
  {
    "clean": {
      "question": "The goal is to declutter one drawer in the kitchen. Is this a short-term or long-term goal? The answer is:",
      "answer": " short"
    },
    "corrupted": {
      "question": "The goal is to design and implement a minimalist zero-clutter home system. Is this a short-term or long-term goal? The answer is:",
      "answer": " long"
    }
  },
  {
    "clean": {
      "question": "The goal is to give a houseplant fresh soil. Is this a short-term or long-term goal? The answer is:",
      "answer": " short"
    },
    "corrupted": {
      "question": "The goal is to develop a global urban reforestation program. Is this a short-term or long-term goal? The answer is:",
      "answer": " long"
    }
  },
  {
    "clean": {
      "question": "The goal is to finish the current sprint's tasks. Is this a short-term or long-term goal? The answer is:",
      "answer": " short"
    },
    "corrupted": {
      "question": "The goal is to build and scale a technology startup. Is this a short-term or long-term goal? The answer is:",
      "answer": " long"
    }
  }
]